pocketmapper/__init__.py
pocketmapper/align.py
pocketmapper/blosum62.bla
pocketmapper/lib.py
pocketmapper/local_aligner.py
pocketmapper/pisa.py
pocketmapper/pocketmapper.py
pocketmapper/human_domains/human
pocketmapper/human_domains/human.dbtype
pocketmapper/human_domains/human.index
pocketmapper/human_domains/human.lookup
pocketmapper/human_domains/human.source
pocketmapper/human_domains/human_ca
pocketmapper/human_domains/human_ca.dbtype
pocketmapper/human_domains/human_ca.index
pocketmapper/human_domains/human_h
pocketmapper/human_domains/human_h.dbtype
pocketmapper/human_domains/human_h.index
pocketmapper/human_domains/human_ss
pocketmapper/human_domains/human_ss.dbtype
pocketmapper/human_domains/human_ss.index
pocketmapper-0.0.7rc0.dist-info/licenses/LICENSE
pocketmapper-0.0.7rc0.dist-info/METADATA
pocketmapper-0.0.7rc0.dist-info/WHEEL
pocketmapper-0.0.7rc0.dist-info/entry_points.txt
pocketmapper-0.0.7rc0.dist-info/top_level.txt
pocketmapper-0.0.7rc0.dist-info/RECORD
