Metadata-Version: 2.4
Name: pocketmapper
Version: 0.0.7rc0
Summary: A tool for mapping surface pockets in PDB structures
Author-email: Lachlan Ellingboe <Lachlan.Ellingboe@icr.ac.uk>
License-Expression: MIT
Classifier: Development Status :: 3 - Alpha
Classifier: Intended Audience :: Science/Research
Classifier: Programming Language :: Python :: 3
Classifier: Programming Language :: Python :: 3.12
Classifier: Operating System :: OS Independent
Requires-Python: >=3.12
License-File: LICENSE
Requires-Dist: bio
Requires-Dist: fire
Requires-Dist: numpy
Requires-Dist: pandas
Requires-Dist: tqdm
Requires-Dist: gemmi
Provides-Extra: dev
Requires-Dist: black; extra == "dev"
Requires-Dist: bump2version; extra == "dev"
Requires-Dist: pre-commit; extra == "dev"
Requires-Dist: flake8; extra == "dev"
Dynamic: license-file
